{
  "export_version": 2,
  "packages": [
    {
      "Id": "Microsoft.DirectX",
      "Name": "DirectX End-User Runtime Web \u2026",
      "Version": "9.29.1974.1",
      "Source": "winget",
      "ManagerName": "Winget",
      "InstallationOptions": {
        "SkipHashCheck": false,
        "InteractiveInstallation": false,
        "RunAsAdministrator": false,
        "Architecture": "",
        "InstallationScope": "",
        "CustomParameters": [],
        "PreRelease": false,
        "CustomInstallLocation": "",
        "Version": ""
      },
      "Updates": {
        "UpdatesIgnored": false,
        "IgnoredVersion": ""
      }
    },
    {
      "Id": "Microsoft.VCRedist.2005.x86",
      "Name": "Microsoft Visual C\u002B\u002B 2005 Redistributable",
      "Version": "8.0.61001",
      "Source": "winget",
      "ManagerName": "Winget",
      "InstallationOptions": {
        "SkipHashCheck": false,
        "InteractiveInstallation": false,
        "RunAsAdministrator": false,
        "Architecture": "",
        "InstallationScope": "",
        "CustomParameters": [],
        "PreRelease": false,
        "CustomInstallLocation": "",
        "Version": ""
      },
      "Updates": {
        "UpdatesIgnored": false,
        "IgnoredVersion": ""
      }
    },
    {
      "Id": "Microsoft.VCRedist.2005.x64",
      "Name": "Microsoft Visual C\u002B\u002B 2005 Redistributable (x64)",
      "Version": "8.0.61000",
      "Source": "winget",
      "ManagerName": "Winget",
      "InstallationOptions": {
        "SkipHashCheck": false,
        "InteractiveInstallation": false,
        "RunAsAdministrator": false,
        "Architecture": "",
        "InstallationScope": "",
        "CustomParameters": [],
        "PreRelease": false,
        "CustomInstallLocation": "",
        "Version": ""
      },
      "Updates": {
        "UpdatesIgnored": false,
        "IgnoredVersion": ""
      }
    },
    {
      "Id": "Microsoft.VCRedist.2008.x64",
      "Name": "Microsoft Visual C\u002B\u002B 2008 Redistributable - x64",
      "Version": "9.0.30729.6161",
      "Source": "winget",
      "ManagerName": "Winget",
      "InstallationOptions": {
        "SkipHashCheck": false,
        "InteractiveInstallation": false,
        "RunAsAdministrator": false,
        "Architecture": "",
        "InstallationScope": "",
        "CustomParameters": [],
        "PreRelease": false,
        "CustomInstallLocation": "",
        "Version": ""
      },
      "Updates": {
        "UpdatesIgnored": false,
        "IgnoredVersion": ""
      }
    },
    {
      "Id": "Microsoft.VCRedist.2008.x86",
      "Name": "Microsoft Visual C\u002B\u002B 2008 Redistributable - x86",
      "Version": "9.0.30729.6161",
      "Source": "winget",
      "ManagerName": "Winget",
      "InstallationOptions": {
        "SkipHashCheck": false,
        "InteractiveInstallation": false,
        "RunAsAdministrator": false,
        "Architecture": "",
        "InstallationScope": "",
        "CustomParameters": [],
        "PreRelease": false,
        "CustomInstallLocation": "",
        "Version": ""
      },
      "Updates": {
        "UpdatesIgnored": false,
        "IgnoredVersion": ""
      }
    },
    {
      "Id": "Microsoft.VCRedist.2010.x64",
      "Name": "Microsoft Visual C\u002B\u002B 2010 x64 Redistributable",
      "Version": "10.0.40219",
      "Source": "winget",
      "ManagerName": "Winget",
      "InstallationOptions": {
        "SkipHashCheck": false,
        "InteractiveInstallation": false,
        "RunAsAdministrator": false,
        "Architecture": "",
        "InstallationScope": "",
        "CustomParameters": [],
        "PreRelease": false,
        "CustomInstallLocation": "",
        "Version": ""
      },
      "Updates": {
        "UpdatesIgnored": false,
        "IgnoredVersion": ""
      }
    },
    {
      "Id": "Microsoft.VCRedist.2010.x86",
      "Name": "Microsoft Visual C\u002B\u002B 2010 x86 Redistributable",
      "Version": "10.0.40219",
      "Source": "winget",
      "ManagerName": "Winget",
      "InstallationOptions": {
        "SkipHashCheck": false,
        "InteractiveInstallation": false,
        "RunAsAdministrator": false,
        "Architecture": "",
        "InstallationScope": "",
        "CustomParameters": [],
        "PreRelease": false,
        "CustomInstallLocation": "",
        "Version": ""
      },
      "Updates": {
        "UpdatesIgnored": false,
        "IgnoredVersion": ""
      }
    },
    {
      "Id": "Microsoft.VCRedist.2012.x64",
      "Name": "Microsoft Visual C\u002B\u002B 2012 Redistributable (x64)",
      "Version": "11.0.61030.0",
      "Source": "winget",
      "ManagerName": "Winget",
      "InstallationOptions": {
        "SkipHashCheck": false,
        "InteractiveInstallation": false,
        "RunAsAdministrator": false,
        "Architecture": "",
        "InstallationScope": "",
        "CustomParameters": [],
        "PreRelease": false,
        "CustomInstallLocation": "",
        "Version": ""
      },
      "Updates": {
        "UpdatesIgnored": false,
        "IgnoredVersion": ""
      }
    },
    {
      "Id": "Microsoft.VCRedist.2012.x86",
      "Name": "Microsoft Visual C\u002B\u002B 2012 Redistributable (x86)",
      "Version": "11.0.61030.0",
      "Source": "winget",
      "ManagerName": "Winget",
      "InstallationOptions": {
        "SkipHashCheck": false,
        "InteractiveInstallation": false,
        "RunAsAdministrator": false,
        "Architecture": "",
        "InstallationScope": "",
        "CustomParameters": [],
        "PreRelease": false,
        "CustomInstallLocation": "",
        "Version": ""
      },
      "Updates": {
        "UpdatesIgnored": false,
        "IgnoredVersion": ""
      }
    },
    {
      "Id": "Microsoft.VCRedist.2013.x64",
      "Name": "Microsoft Visual C\u002B\u002B 2013 Redistributable (x64)",
      "Version": "12.0.40664.0",
      "Source": "winget",
      "ManagerName": "Winget",
      "InstallationOptions": {
        "SkipHashCheck": false,
        "InteractiveInstallation": false,
        "RunAsAdministrator": false,
        "Architecture": "",
        "InstallationScope": "",
        "CustomParameters": [],
        "PreRelease": false,
        "CustomInstallLocation": "",
        "Version": ""
      },
      "Updates": {
        "UpdatesIgnored": false,
        "IgnoredVersion": ""
      }
    },
    {
      "Id": "Microsoft.VCRedist.2013.x86",
      "Name": "Microsoft Visual C\u002B\u002B 2013 Redistributable (x86)",
      "Version": "12.0.40664.0",
      "Source": "winget",
      "ManagerName": "Winget",
      "InstallationOptions": {
        "SkipHashCheck": false,
        "InteractiveInstallation": false,
        "RunAsAdministrator": false,
        "Architecture": "",
        "InstallationScope": "",
        "CustomParameters": [],
        "PreRelease": false,
        "CustomInstallLocation": "",
        "Version": ""
      },
      "Updates": {
        "UpdatesIgnored": false,
        "IgnoredVersion": ""
      }
    },
    {
      "Id": "Microsoft.VCRedist.2015\u002B.x64",
      "Name": "Microsoft Visual C\u002B\u002B 2015-2022 Redistributable (x64)",
      "Version": "14.38.33135.0",
      "Source": "winget",
      "ManagerName": "Winget",
      "InstallationOptions": {
        "SkipHashCheck": false,
        "InteractiveInstallation": false,
        "RunAsAdministrator": false,
        "Architecture": "",
        "InstallationScope": "",
        "CustomParameters": [],
        "PreRelease": false,
        "CustomInstallLocation": "",
        "Version": ""
      },
      "Updates": {
        "UpdatesIgnored": false,
        "IgnoredVersion": ""
      }
    },
    {
      "Id": "Microsoft.VCRedist.2015\u002B.x86",
      "Name": "Microsoft Visual C\u002B\u002B 2015-2022 Redistributable (x86)",
      "Version": "14.38.33135.0",
      "Source": "winget",
      "ManagerName": "Winget",
      "InstallationOptions": {
        "SkipHashCheck": false,
        "InteractiveInstallation": false,
        "RunAsAdministrator": false,
        "Architecture": "",
        "InstallationScope": "",
        "CustomParameters": [],
        "PreRelease": false,
        "CustomInstallLocation": "",
        "Version": ""
      },
      "Updates": {
        "UpdatesIgnored": false,
        "IgnoredVersion": ""
      }
    }
  ],
  "incompatible_packages_info": "Incompatible packages cannot be installed from WingetUI, but they have been listed here for logging purposes.",
  "incompatible_packages": []
}